ward/__init__.py
ward/__main__.py
ward/models.py
ward/scanner.py
ward/server.py
ward/analyzer/__init__.py
ward/analyzer/concepts.py
ward/analyzer/engine.py
ward/analyzer/relationships.py
ward/analyzer/adapters/__init__.py
ward/analyzer/adapters/base.py
ward/analyzer/adapters/python.py
ward/services/__init__.py
ward/services/cache.py
ward/services/graph.py
ward/services/llm.py
ward/utilities/__init__.py
ward/utilities/tracing.py
ward/utilities/utils.py
ward_mcp-0.1.2.dist-info/METADATA
ward_mcp-0.1.2.dist-info/WHEEL
ward_mcp-0.1.2.dist-info/entry_points.txt
ward_mcp-0.1.2.dist-info/top_level.txt
ward_mcp-0.1.2.dist-info/RECORD
