Metadata-Version: 2.4
Name: ward-mcp
Version: 0.1.2
Summary: MCP server for AI-powered code quality analysis
Requires-Python: >=3.10
Requires-Dist: mcp>=1.0.0
Requires-Dist: pydantic>=2.0.0
Requires-Dist: httpx>=0.25.0
Provides-Extra: llm
Requires-Dist: anthropic>=0.30.0; extra == "llm"
Provides-Extra: graph
Requires-Dist: networkx>=3.0; extra == "graph"
Provides-Extra: analyzer
Requires-Dist: tree-sitter>=0.23.0; extra == "analyzer"
Requires-Dist: tree-sitter-python>=0.23.0; extra == "analyzer"
Requires-Dist: tree-sitter-javascript>=0.23.0; extra == "analyzer"
Requires-Dist: tree-sitter-go>=0.23.0; extra == "analyzer"
Requires-Dist: pyyaml>=6.0; extra == "analyzer"
Provides-Extra: dev
Requires-Dist: pytest>=7.0.0; extra == "dev"
Requires-Dist: mypy>=1.0.0; extra == "dev"
